{
  "config": {
    "population_size": 100,
    "number_of_generations": 1000,
    "percent_of_parents": 0.5,
    "percent_of_mutations_type": 0.5,
    "percent_of_mutations_rotation": 0.5,
    "percent_of_mutations_x": 0.5,
    "percent_of_mutations_y": 1,
    "game_path": "abwin/win_build.exe",
    "write_path": "abwin/win_build_Data/StreamingAssets/Levels",
    "read_path": "abwin/win_build_Data/StreamingAssets/Output",
    "log_dir": "logs",
    "log_base_name": "base_large"
  },
  "execution_time": 830.9202206134796,
  "execution": {
    "0000": {
      "entropy": 4.435058587909841,
      "best": 208.89107133333334,
      "avg": 659.4300702781433,
      "worst": 763.377324
    },
    "0001": {
      "entropy": 4.2088408591051385,
      "best": 208.89107133333334,
      "avg": 639.7783954180604,
      "worst": 703.377324
    },
    "0002": {
      "entropy": 4.021405371993919,
      "best": 10.732359074,
      "avg": 624.3754372628752,
      "worst": 683.377324
    },
    "0003": {
      "entropy": 3.9789468859407253,
      "best": 10.732359074,
      "avg": 607.3104855366396,
      "worst": 665.4773240000001
    },
    "0004": {
      "entropy": 4.015043290685094,
      "best": 10.732359074,
      "avg": 606.7510125433064,
      "worst": 665.4773240000001
    },
    "0005": {
      "entropy": 3.8824802119383954,
      "best": 10.732359074,
      "avg": 601.2784703524502,
      "worst": 651.9411183061088
    },
    "0006": {
      "entropy": 3.2671105831212124,
      "best": 10.732359074,
      "avg": 596.2455927640283,
      "worst": 645.4773240000001
    },
    "0007": {
      "entropy": 3.2644724577944393,
      "best": 10.732359074,
      "avg": 587.5074751183478,
      "worst": 643.377324
    },
    "0008": {
      "entropy": 3.364921406876357,
      "best": 10.732359074,
      "avg": 581.5649511987644,
      "worst": 643.377324
    },
    "0009": {
      "entropy": 3.4168939326060794,
      "best": 10.732359074,
      "avg": 580.2726748249604,
      "worst": 643.377324
    },
    "0010": {
      "entropy": 3.817951095964421,
      "best": 10.732359074,
      "avg": 570.5104955893695,
      "worst": 643.377324
    },
    "0011": {
      "entropy": 3.817951095964421,
      "best": 10.732359074,
      "avg": 570.5104955893695,
      "worst": 643.377324
    },
    "0012": {
      "entropy": 3.817951095964421,
      "best": 10.732359074,
      "avg": 568.1493798636337,
      "worst": 633.3558420718127
    },
    "0013": {
      "entropy": 3.817951095964421,
      "best": 10.732359074,
      "avg": 557.0346598701367,
      "worst": 627.5773240000001
    },
    "0014": {
      "entropy": 3.8504022209427866,
      "best": 10.732359074,
      "avg": 554.8551310969583,
      "worst": 627.5773240000001
    },
    "0015": {
      "entropy": 3.7612053755573465,
      "best": 10.732359074,
      "avg": 547.719061034665,
      "worst": 624.3030493
    },
    "0016": {
      "entropy": 3.5961335216142394,
      "best": 10.732359074,
      "avg": 544.439332721965,
      "worst": 623.5300186476368
    },
    "0017": {
      "entropy": 3.6761335216142395,
      "best": 10.732359074,
      "avg": 535.9610239103396,
      "worst": 623.377324
    },
    "0018": {
      "entropy": 3.8166845849422018,
      "best": 10.732359074,
      "avg": 530.6990915688846,
      "worst": 623.377324
    },
    "0019": {
      "entropy": 4.09404750070879,
      "best": 10.732359074,
      "avg": 523.168009754459,
      "worst": 623.377324
    },
    "0020": {
      "entropy": 4.298570107275748,
      "best": 10.732359074,
      "avg": 518.7828290021889,
      "worst": 623.377324
    },
    "0021": {
      "entropy": 4.499843599947983,
      "best": 10.732359074,
      "avg": 514.472884001503,
      "worst": 623.377324
    },
    "0022": {
      "entropy": 4.499843599947983,
      "best": 10.732359074,
      "avg": 514.472884001503,
      "worst": 623.377324
    },
    "0023": {
      "entropy": 4.827341345230696,
      "best": 10.732359074,
      "avg": 505.787517078727,
      "worst": 623.377324
    },
    "0024": {
      "entropy": 4.955274166548142,
      "best": 10.732359074,
      "avg": 499.5815386472984,
      "worst": 623.377324
    },
    "0025": {
      "entropy": 5.2663772977870185,
      "best": 10.732359074,
      "avg": 489.80335357549455,
      "worst": 623.377324
    },
    "0026": {
      "entropy": 5.386922095337587,
      "best": 10.732359074,
      "avg": 484.4452307471612,
      "worst": 623.377324
    },
    "0027": {
      "entropy": 5.732472662218145,
      "best": 10.732359074,
      "avg": 471.61072732462844,
      "worst": 623.377324
    },
    "0028": {
      "entropy": 5.732472662218145,
      "best": 10.732359074,
      "avg": 471.61072732462844,
      "worst": 623.377324
    }
  }
}